illufly_upload/__init__.py
illufly_upload/__main__.py
illufly_upload/endpoints.py
illufly_upload/mcp_client.py
illufly_upload/mcp_server.py
illufly_upload/upload.py
illufly_upload-0.1.1.dist-info/METADATA
illufly_upload-0.1.1.dist-info/WHEEL
illufly_upload-0.1.1.dist-info/entry_points.txt
illufly_upload-0.1.1.dist-info/RECORD
