Metadata-Version: 2.3
Name: illufly-upload
Version: 0.1.1
Summary: 文件上传存储服务
Author: arcstep
Author-email: 43801@qq.com
Requires-Python: >=3.11
Classifier: Programming Language :: Python :: 3
Classifier: Programming Language :: Python :: 3.11
Classifier: Programming Language :: Python :: 3.12
Classifier: Programming Language :: Python :: 3.13
Requires-Dist: aiofiles (>=0.8.0)
Requires-Dist: aiohttp (>=3.11.16,<4.0.0)
Requires-Dist: anyio (>=3.7.0)
Requires-Dist: click (>=8.0.0)
Requires-Dist: fastapi (>=0.68.0)
Requires-Dist: loguru (>=0.5.3)
Requires-Dist: mcp (>=1.6.0,<2.0.0)
Requires-Dist: pydantic (>=1.8.2)
Requires-Dist: python-dotenv (>=0.19.0)
Requires-Dist: python-multipart (>=0.0.5)
Requires-Dist: uvicorn (>=0.15.0)
